s3lync/__init__.py
s3lync/async_client.py
s3lync/async_core.py
s3lync/client.py
s3lync/core.py
s3lync/exceptions.py
s3lync/hash.py
s3lync/logging.py
s3lync/progress.py
s3lync/retry.py
s3lync/utils.py
s3lync-0.4.2.dist-info/licenses/LICENSE
s3lync-0.4.2.dist-info/METADATA
s3lync-0.4.2.dist-info/WHEEL
s3lync-0.4.2.dist-info/top_level.txt
s3lync-0.4.2.dist-info/RECORD
