Metadata-Version: 2.4
Name: s3lync
Version: 0.4.2
Summary: The Pythonic Bridge Between S3 and the Local Filesystem. Use S3 objects like local files with automatic sync.
Author-email: JunSeok Kim <infend@gmail.com>
License: MIT
Project-URL: Homepage, https://github.com/bestend/s3lync
Project-URL: Documentation, https://github.com/bestend/s3lync
Project-URL: Repository, https://github.com/bestend/s3lync.git
Project-URL: Issues, https://github.com/bestend/s3lync/issues
Project-URL: Changelog, https://github.com/bestend/s3lync/blob/main/CHANGELOG.md
Keywords: s3,aws,sync,filesystem,s3-sync
Classifier: Development Status :: 3 - Alpha
Classifier: Intended Audience :: Developers
Classifier: License :: OSI Approved :: MIT License
Classifier: Programming Language :: Python :: 3
Classifier: Programming Language :: Python :: 3.9
Classifier: Programming Language :: Python :: 3.10
Classifier: Programming Language :: Python :: 3.11
Classifier: Programming Language :: Python :: 3.12
Classifier: Topic :: Software Development :: Libraries :: Python Modules
Classifier: Topic :: Software Development :: Libraries
Requires-Python: >=3.9
License-File: LICENSE
Requires-Dist: boto3>=1.26.0
Requires-Dist: boto3-stubs~=1.42.14
Requires-Dist: botocore>=1.29.0
Requires-Dist: tqdm>=4.60.0
Provides-Extra: async
Requires-Dist: aioboto3>=12.0.0; extra == "async"
Provides-Extra: dev
Requires-Dist: pytest>=7.0; extra == "dev"
Requires-Dist: pytest-cov>=4.0; extra == "dev"
Requires-Dist: pytest-mock>=3.0; extra == "dev"
Requires-Dist: ruff>=0.0.250; extra == "dev"
Requires-Dist: mypy>=1.0; extra == "dev"
Requires-Dist: pytest-asyncio>=0.21.0; extra == "dev"
Requires-Dist: aioboto3>=12.0.0; extra == "dev"
Dynamic: license-file
